README.rst
flask_upstatic.py
setup.py
Flask_Upstatic.egg-info/PKG-INFO
Flask_Upstatic.egg-info/SOURCES.txt
Flask_Upstatic.egg-info/dependency_links.txt
Flask_Upstatic.egg-info/pbr.json
Flask_Upstatic.egg-info/requires.txt
Flask_Upstatic.egg-info/top_level.txt