Metadata-Version: 1.0
Name: Flask-Upstatic
Version: 0.0.6
Summary: Opinionated library for working with CDNs in Flask.
Home-page: https://github.com/insynchq/flask-upstatic
Author: Mark Steve Samson
Author-email: marksteve@insynchq.com
License: MIT
Platform: UNKNOWN
